hlc/helpers.py
hlc/cli.py
hlc/hostlist.py
hlc/__init__.py
hlc/_meta.py
hlc-0.3.0.dist-info/entry_points.txt
hlc-0.3.0.dist-info/top_level.txt
hlc-0.3.0.dist-info/METADATA
hlc-0.3.0.dist-info/DESCRIPTION.rst
hlc-0.3.0.dist-info/metadata.json
hlc-0.3.0.dist-info/WHEEL
hlc-0.3.0.dist-info/RECORD
