Metadata-Version: 2.0
Name: hlc
Version: 0.3.0
Summary: Host list converter supporting hosts(5), ethers(5) and other formats
Home-page: https://github.com/ypid/hlc
Author: Robin Schneider
Author-email: ypid@riseup.net
License: AGPL-3.0
Keywords: workstations host list converter ethers mac-address
Platform: UNKNOWN
Classifier: Development Status :: 4 - Beta
Classifier: Environment :: Console
Classifier: Intended Audience :: Developers
Classifier: Intended Audience :: System Administrators
Classifier: License :: DFSG approved
Classifier: License :: OSI Approved :: GNU Affero General Public License v3
Classifier: Natural Language :: English
Classifier: Operating System :: OS Independent
Classifier: Programming Language :: Python :: 3.4
Classifier: Programming Language :: Python :: 3.5
Classifier: Topic :: System :: Systems Administration
Classifier: Topic :: Text Processing
Requires-Dist: netaddr (>=0.7.18)
Provides-Extra: test
Requires-Dist: nose; extra == 'test'
Requires-Dist: nose2; extra == 'test'
Requires-Dist: tox; extra == 'test'
